pysplus/Client.py
pysplus/Update.py
pysplus/__init__.py
pysplus/async_sync.py
pysplus/colors.py
pysplus/props.py
pysplus-0.8.2.dist-info/METADATA
pysplus-0.8.2.dist-info/WHEEL
pysplus-0.8.2.dist-info/top_level.txt
pysplus-0.8.2.dist-info/RECORD
