Metadata-Version: 2.4
Name: PySPlus
Version: 0.8.2
Summary: the library SPlus platform for bots.
Home-page: https://github.com/OandONE/SPlus
Author: seyyed mohamad hosein moosavi raja(01)
Author-email: mohamadhosein159159@gmail.com
License: MIT
Requires-Python: >=3.8
Requires-Dist: selenium==4.29.0
Requires-Dist: webdriver_manager==4.0.2
Requires-Dist: bs4==0.0.2
Requires-Dist: pytz
Dynamic: author
Dynamic: author-email
Dynamic: description
Dynamic: description-content-type
Dynamic: home-page
Dynamic: license
Dynamic: requires-dist
Dynamic: requires-python
Dynamic: summary
